README.md
setup.py
ediri_fly/__init__.py
ediri_fly/_inputs.py
ediri_fly/_utilities.py
ediri_fly/app.py
ediri_fly/cert.py
ediri_fly/get_app.py
ediri_fly/get_cert.py
ediri_fly/get_ip.py
ediri_fly/get_volume.py
ediri_fly/ip.py
ediri_fly/machine.py
ediri_fly/outputs.py
ediri_fly/provider.py
ediri_fly/pulumi-plugin.json
ediri_fly/py.typed
ediri_fly/volume.py
ediri_fly.egg-info/PKG-INFO
ediri_fly.egg-info/SOURCES.txt
ediri_fly.egg-info/dependency_links.txt
ediri_fly.egg-info/not-zip-safe
ediri_fly.egg-info/requires.txt
ediri_fly.egg-info/top_level.txt
ediri_fly/config/__init__.py
ediri_fly/config/vars.py