Metadata-Version: 2.1
Name: ediri-fly
Version: 0.1.16
Summary: A Pulumi package for creating and managing Fly.io resources.
Home-page: https://github.com/dirien/pulumi-fly
License: Apache-2.0
Project-URL: Repository, https://github.com/dirien/pulumi-fly
Keywords: pulumi fly category/cloud
Platform: UNKNOWN
Requires-Python: >=3.8
